{
    "metadata": {
        "Name": "",
        "Subsets": [],
        "Link": "https://github.com/cambridgeltl/xcopa}{\\texttt{github.com/cambridgeltl/xcopa}}.",
        "HF Link": "https://huggingface.co/bert-base-multilingual-cased}}",
        "License": "Apache-1.0",
        "Year": 2025,
        "Language": [
            "Arabic"
        ],
        "Domain": [
            "books",
            "wikipedia",
            "web pages"
        ],
        "Form": "text",
        "Collection Style": [
            "crawling"
        ],
        "Description": "",
        "Volume": 0.0,
        "Unit": "tokens",
        "Ethical Risks": "Low",
        "Provider": [],
        "Derived From": [],
        "Paper Title": "",
        "Paper Link": "https://arxiv.org/abs/2005.00333",
        "Tokenized": false,
        "Host": "CAMeL Resources",
        "Access": "Free",
        "Cost": "",
        "Test Split": true,
        "Tasks": [
            "machine translation",
            "sentiment analysis",
            "language modeling",
            "question answering",
            "natural language inference",
            "commonsense reasoning",
            "other"
        ],
        "Venue Title": "",
        "Venue Type": "conference",
        "Venue Name": "",
        "Authors": [],
        "Affiliations": [],
        "Abstract": ""
    },
    "validation": {
        "DIVERSITY": 0.0,
        "ACCESSABILITY": 0.2857142857142857,
        "CONTENT": 0.2857142857142857,
        "EVALUATION": 0.0,
        "AVERAGE": 0.21052631578947367
    },
    "length_forcing": 0.8333333333333333,
    "cost": {
        "cost": 0,
        "input_tokens": 0,
        "output_tokens": 0
    },
    "config": {
        "model_name": "baseline-keyword",
        "few_shot": 0,
        "month": null,
        "year": "2020",
        "keywords": [
            ""
        ],
        "link": "https://arxiv.org/abs/2005.00333"
    },
    "ratio_filling": 1.0,
    "error": null
}