{
    "metadata": {
        "Name": "",
        "Link": "https://www.etalab.gouv.fr/wp-content/uploads/2017/04/ETALAB-Licence-Ouverte-v2.0.pdf}{Open",
        "HF Link": "https://huggingface.co/datasets/OpenLLM-France/Claire-Dialogue-French-0.1}{https://huggingface.co/datasets/OpenLLM-France/Claire-Dialogue-French-0.1}}",
        "License": "Apache-1.0",
        "Year": 2025,
        "Language": "fr",
        "Domain": [
            "books",
            "web pages"
        ],
        "Form": "text",
        "Collection Style": [
            "manual curation"
        ],
        "Description": "",
        "Volume": 0.0,
        "Unit": "documents",
        "Ethical Risks": "Low",
        "Provider": [],
        "Derived From": [],
        "Paper Title": "",
        "Paper Link": "https://arxiv.org/abs/2311.16840",
        "Tokenized": false,
        "Host": "CAMeL Resources",
        "Access": "Free",
        "Cost": "",
        "Test Split": true,
        "Tasks": [
            "speech recognition",
            "summarization",
            "instruction tuning",
            "optical character recognition",
            "other"
        ],
        "Venue Title": "",
        "Venue Type": "conference",
        "Venue Name": "",
        "Authors": [],
        "Affiliations": [],
        "Abstract": ""
    },
    "validation": {
        "ACCESSABILITY": 0.2857142857142857,
        "DIVERSITY": 1.0,
        "CONTENT": 0.5714285714285714,
        "EVALUATION": 0.3333333333333333,
        "AVERAGE": 0.4444444444444444
    },
    "length_forcing": 0.8965517241379307,
    "cost": {
        "cost": 0,
        "input_tokens": 0,
        "output_tokens": 0
    },
    "config": {
        "model_name": "baseline-keyword",
        "few_shot": 0,
        "month": null,
        "year": "2023",
        "keywords": [
            ""
        ],
        "link": "https://arxiv.org/abs/2311.16840"
    },
    "ratio_filling": 1.0,
    "error": null
}