{
    "metadata": {
        "Name": "OpenITI",
        "Subsets": [
            {
                "Name": "Egypt",
                "Volume": "Unknown",
                "Unit": "documents",
                "Dialect": "Egypt"
            },
            {
                "Name": "Saudi Arabia",
                "Volume": "Unknown",
                "Unit": "documents",
                "Dialect": "Saudi Arabia"
            },
            {
                "Name": "Iraq",
                "Volume": "Unknown",
                "Unit": "documents",
                "Dialect": "Iraq"
            },
            {
                "Name": "Syria",
                "Volume": "Unknown",
                "Unit": "documents",
                "Dialect": "Syria"
            },
            {
                "Name": "Morocco",
                "Volume": "Unknown",
                "Unit": "documents",
                "Dialect": "Morocco"
            },
            {
                "Name": "Levant",
                "Volume": "Unknown",
                "Unit": "documents",
                "Dialect": "Levant"
            },
            {
                "Name": "North Africa",
                "Volume": "Unknown",
                "Unit": "documents",
                "Dialect": "North Africa"
            }
        ],
        "Link": "https://github.com/OpenITI",
        "HF Link": "",
        "License": "unknown",
        "Year": 2016,
        "Language": "ar",
        "Dialect": "Modern Standard Arabic",
        "Domain": [
            "books",
            "news articles",
            "news articles"
        ],
        "Form": "text",
        "Collection Style": [
            "crawling",
            "manual curation"
        ],
        "Description": "A large-scale historical corpus of the written Arabic language, spanning 1400 years.",
        "Volume": 1500000000.0,
        "Unit": "tokens",
        "Ethical Risks": "Medium",
        "Provider": [
            "Qatar Computing Research Institute",
            "MIT Computer Science and Artificial Intelligence Laboratory",
            "University of Rhode Island",
            "Bar-Ilan University",
            "University of Vienna"
        ],
        "Derived From": [
            "Shamela"
        ],
        "Paper Title": "Studying the History of the Arabic Language Language Technology and a Large-Scale Historical Corpus",
        "Paper Link": "https://arxiv.org/abs/1809.03891",
        "Script": "Arab",
        "Tokenized": false,
        "Host": "GitHub",
        "Access": "Free",
        "Cost": "",
        "Test Split": false,
        "Tasks": [
            "language modeling",
            "natural language inference",
            "speaker identification",
            "fake news detection"
        ],
        "Venue Title": "",
        "Venue Type": "preprint",
        "Venue Name": "",
        "Authors": [
            "Yonatan Belinkov",
            "Alexander Magidow",
            "Alberto Barr\u00f3n-Cede\u00f1o",
            "Avi Shmidman",
            "Maxim Romanov"
        ],
        "Affiliations": [
            "MIT Computer Science and Artificial Intelligence Laboratory",
            "University of Rhode Island",
            "Qatar Computing Research Institute",
            "Bar-Ilan University",
            "University of Vienna"
        ],
        "Abstract": "Arabic is a widely-spoken language with a long and rich history, but existing corpora and language technology focus mostly on modern Arabic and its varieties. Therefore, studying the history of the language has so far been mostly limited to manual analyses on a small scale. In this work, we present a large-scale historical corpus of the written Arabic language, spanning 1400 years. We describe our efforts to clean and process this corpus using Arabic NLP tools, including the identification of reused text. We study the history of the Arabic language using a novel automatic periodization algorithm, as well as other techniques. Our findings confirm the established division of written Arabic into Modern Standard and Classical Arabic, and confirm other established periodizations, while suggesting that written Arabic may be divisible into still further periods of development."
    },
    "validation": {
        "DIVERSITY": 0.3333333333333333,
        "ACCESSABILITY": 0.42857142857142855,
        "CONTENT": 0.375,
        "EVALUATION": 0.6666666666666666,
        "AVERAGE": 0.42857142857142855
    },
    "length_forcing": 1.0,
    "cost": {
        "cost": 0.0029806,
        "input_tokens": 25031,
        "output_tokens": 846
    },
    "config": {
        "model_name": "google_gemma-3-27b-it",
        "few_shot": 0,
        "month": null,
        "year": "2018",
        "keywords": [
            ""
        ],
        "link": "https://arxiv.org/abs/1809.03891"
    },
    "ratio_filling": 1.0,
    "error": null
}