{
    "metadata": {
        "Name": "",
        "Link": "http://clic.cimec.unitn.it/lambada/}}}",
        "HF Link": "",
        "License": "Apache-1.0",
        "Year": 2025,
        "Language": "en",
        "Domain": [
            "news articles",
            "books",
            "wikipedia"
        ],
        "Form": "text",
        "Collection Style": [
            "manual curation"
        ],
        "Description": "",
        "Volume": 0.0,
        "Unit": "tokens",
        "Ethical Risks": "Low",
        "Provider": [],
        "Derived From": [],
        "Paper Title": "",
        "Paper Link": "https://arxiv.org/abs/1606.06031",
        "Tokenized": false,
        "Host": "CAMeL Resources",
        "Access": "Free",
        "Cost": "",
        "Test Split": true,
        "Tasks": [
            "language modeling",
            "word prediction",
            "other"
        ],
        "Venue Title": "",
        "Venue Type": "conference",
        "Venue Name": "",
        "Authors": [],
        "Affiliations": [],
        "Abstract": ""
    },
    "validation": {
        "ACCESSABILITY": 0.2857142857142857,
        "DIVERSITY": 1.0,
        "CONTENT": 0.42857142857142855,
        "EVALUATION": 0.3333333333333333,
        "AVERAGE": 0.3888888888888889
    },
    "length_forcing": 0.8965517241379307,
    "cost": {
        "cost": 0,
        "input_tokens": 0,
        "output_tokens": 0
    },
    "config": {
        "model_name": "baseline-keyword",
        "few_shot": 0,
        "month": null,
        "year": "2016",
        "keywords": [
            ""
        ],
        "link": "https://arxiv.org/abs/1606.06031"
    },
    "ratio_filling": 1.0,
    "error": null
}